ion_oauth/__init__.py
ion_oauth/oauth.py
ion_oauth-0.1.dist-info/DESCRIPTION.rst
ion_oauth-0.1.dist-info/METADATA
ion_oauth-0.1.dist-info/RECORD
ion_oauth-0.1.dist-info/WHEEL
ion_oauth-0.1.dist-info/metadata.json
ion_oauth-0.1.dist-info/top_level.txt
ion_oauth-0.1.dist-info/zip-safe
