Metadata-Version: 1.1
Name: ion_oauth
Version: 0.1
Summary: python-social-auth plugin for ion
Home-page: https://github.com/tjcsl/ion_oauth
Author: The TJHSST Computer Systems Lab
Author-email: intranet@tjhsst.edu
License: GPL
Platform: UNKNOWN
Classifier: Development Status :: 5 - Production/Stable
Classifier: License :: OSI Approved :: GNU General Public License v2 or later (GPLv2+)
Classifier: Operating System :: POSIX :: Linux
Classifier: Programming Language :: Python :: 2
Classifier: Programming Language :: Python :: 3
